LICENSE.txt
MANIFEST.in
README.rst
Tool.py
setup.py
sztestlib/__init__.py
sztestlib/szlibone.py
sztestliblib.egg-info/PKG-INFO
sztestliblib.egg-info/SOURCES.txt
sztestliblib.egg-info/dependency_links.txt
sztestliblib.egg-info/top_level.txt