Metadata-Version: 1.0
Name: sztestliblib
Version: 1.0.1
Summary: this is a  ni lib
Home-page: https://github.com/pypa/sampleproject
Author: sz
Author-email: 962296332@qq.com
License: MIT
Platform: UNKNOWN
